{"cameraMode":{"drawMode":0,"name":"Shaded","section":"Shading Mode"},"sceneLighting":false,"audioPlay":false,"sceneViewState":{"m_AlwaysRefresh":false,"showFog":true,"showSkybox":false,"showFlares":true,"showImageEffects":true,"showParticleSystems":true,"showVisualEffectGraphs":true,"m_FxEnabled":true},"in2DMode":false,"pivot":{"x":2.630744218826294,"y":16.53339195251465,"z":237.935302734375},"rotation":{"x":-0.011714736931025982,"y":0.0024124321062117817,"z":-0.000027648693503579125,"w":-0.9999568462371826},"size":137.34255981445313,"orthographic":false}